{
    "status": "OK",
    "request_id": "4fd12b1c-b3ee-42ce-80e8-a38bd08d904c",
    "parameters": {
        "query": "NLP Data Scientist Junior Machine Learning AI",
        "page": 1,
        "num_pages": 1,
        "date_posted": "today",
        "country": "us",
        "language": "en"
    },
    "data": [
        {
            "job_id": "SdpAHE9YBbRV9tJBAAAAAA==",
            "job_title": "NLP Engineer",
            "employer_name": "Jobleads-US",
            "employer_logo": "https://encrypted-tbn0.gstatic.com/images?q=tbn:ANd9GcRDw89Ju35iZBMq12Dxvatoi3VVaj94uzEQbO11&s=0",
            "employer_website": null,
            "job_publisher": "BeBee",
            "job_employment_type": "Full-time",
            "job_employment_types": [
                "FULLTIME"
            ],
            "job_apply_link": "https://us.bebee.com/job/a8792501eaf05ea8bb94eb442ff0d14d?utm_campaign=google_jobs_apply&utm_source=google_jobs_apply&utm_medium=organic",
            "job_apply_is_direct": false,
            "apply_options": [
                {
                    "publisher": "BeBee",
                    "apply_link": "https://us.bebee.com/job/a8792501eaf05ea8bb94eb442ff0d14d?utm_campaign=google_jobs_apply&utm_source=google_jobs_apply&utm_medium=organic",
                    "is_direct": false
                },
                {
                    "publisher": "Jobs Trabajo.org",
                    "apply_link": "https://us.trabajo.org/job-2850-e294c6fbdef52795dbed8924fc5b615d?utm_campaign=google_jobs_apply&utm_source=google_jobs_apply&utm_medium=organic",
                    "is_direct": false
                },
                {
                    "publisher": "Joinu",
                    "apply_link": "https://joinu.com/software-developers-jobs/washington-dc/nlp-engineer/327207470?utm_campaign=google_jobs_apply&utm_source=google_jobs_apply&utm_medium=organic",
                    "is_direct": false
                }
            ],
            "job_description": "Job Title: NLP Engineer\nAbout the Role\n\nWe are seeking a highly skilled NLP Engineer to join our team at JobLeads-US. As an NLP Engineer, you will play a crucial role in designing and developing cutting-edge information retrieval systems that will shape the future of legal technology.\nKey Responsibilities\n\u2022 Design and implement advanced information retrieval systems using NLP techniques, embeddings, and vector databases to improve relevance and efficiency.\n\u2022 Assess requirements and choose appropriate technologies to develop scalable, maintainable search solutions.\n\u2022 Build reliable pipelines for processing PDFs, extracting text, named entities, and key information.\n\u2022 Configure search engines, develop search APIs, and integrate vector databases to enhance similarity scoring.\n\u2022 Fine-tune and optimize NLP models to improve search precision and relevance.\n\u2022 Create and maintain APIs for smooth communication between application components.\n\u2022 Identify and resolve system bottlenecks to improve retrieval speed and accuracy.\nRequirements\n\u2022 At least 5 years of experience in NLP, information retrieval, and search technologies (e.g. Elasticsearch, OpenSearch, FAISS, Pinecone).\n\u2022 Expertise in vector-based search, embeddings, and similarity scoring techniques.\n\u2022 Practical experience with PDF processing, text extraction, and named entity recognition (NER).\n\u2022 Proficiency in deep learning frameworks (TensorFlow, PyTorch) and NLP libraries (Hugging Face, spaCy, NLTK).\n\u2022 Experience in developing and maintaining scalable APIs (REST, GraphQL, gRPC).\n\u2022 Strong Python skills with familiarity in cloud platforms such as AWS, GCP, or Azure.\n\u2022 Proven track record of optimizing system performance and managing large-scale search workloads.\n\u2022 Knowledge of knowledge graphs, ontologies, or semantic search is a plus.",
            "job_is_remote": false,
            "job_posted_at": "10 hours ago",
            "job_posted_at_timestamp": 1750028400,
            "job_posted_at_datetime_utc": "2025-06-15T23:00:00.000Z",
            "job_location": "Washington, DC",
            "job_city": "Washington",
            "job_state": "District of Columbia",
            "job_country": "US",
            "job_latitude": 38.9071923,
            "job_longitude": -77.0368707,
            "job_benefits": null,
            "job_google_link": "https://www.google.com/search?q=jobs&gl=us&hl=en&udm=8#vhid=vt%3D20/docid%3DSdpAHE9YBbRV9tJBAAAAAA%3D%3D&vssid=jobs-detail-viewer",
            "job_salary": null,
            "job_min_salary": null,
            "job_max_salary": null,
            "job_salary_period": null,
            "job_highlights": {
                "Qualifications": [
                    "At least 5 years of experience in NLP, information retrieval, and search technologies (e.g. Elasticsearch, OpenSearch, FAISS, Pinecone)",
                    "Expertise in vector-based search, embeddings, and similarity scoring techniques",
                    "Practical experience with PDF processing, text extraction, and named entity recognition (NER)",
                    "Proficiency in deep learning frameworks (TensorFlow, PyTorch) and NLP libraries (Hugging Face, spaCy, NLTK)",
                    "Experience in developing and maintaining scalable APIs (REST, GraphQL, gRPC)",
                    "Strong Python skills with familiarity in cloud platforms such as AWS, GCP, or Azure",
                    "Proven track record of optimizing system performance and managing large-scale search workloads"
                ],
                "Responsibilities": [
                    "As an NLP Engineer, you will play a crucial role in designing and developing cutting-edge information retrieval systems that will shape the future of legal technology",
                    "Design and implement advanced information retrieval systems using NLP techniques, embeddings, and vector databases to improve relevance and efficiency",
                    "Assess requirements and choose appropriate technologies to develop scalable, maintainable search solutions",
                    "Build reliable pipelines for processing PDFs, extracting text, named entities, and key information",
                    "Configure search engines, develop search APIs, and integrate vector databases to enhance similarity scoring",
                    "Fine-tune and optimize NLP models to improve search precision and relevance",
                    "Create and maintain APIs for smooth communication between application components",
                    "Identify and resolve system bottlenecks to improve retrieval speed and accuracy"
                ]
            },
            "job_onet_soc": "15111100",
            "job_onet_job_zone": "5"
        },
        {
            "job_id": "q6rqDBIOnPAT4350AAAAAA==",
            "job_title": "NLP Analyst",
            "employer_name": "Capgemini",
            "employer_logo": "https://encrypted-tbn0.gstatic.com/images?q=tbn:ANd9GcT5BSMIt7m2uiId_3142LNElhU-kvf9h48rIEOM&s=0",
            "employer_website": "http://www.capgemini.com/",
            "job_publisher": "Jobs Trabajo.org",
            "job_employment_type": "Full-time",
            "job_employment_types": [
                "FULLTIME"
            ],
            "job_apply_link": "https://us.trabajo.org/job-2850-6c87b4040bd6da0cb8039adda6d649b7?utm_campaign=google_jobs_apply&utm_source=google_jobs_apply&utm_medium=organic",
            "job_apply_is_direct": false,
            "apply_options": [
                {
                    "publisher": "Jobs Trabajo.org",
                    "apply_link": "https://us.trabajo.org/job-2850-6c87b4040bd6da0cb8039adda6d649b7?utm_campaign=google_jobs_apply&utm_source=google_jobs_apply&utm_medium=organic",
                    "is_direct": false
                }
            ],
            "job_description": "Select how often (in days) to receive an alert:\nNLP Analyst - Conversational Designer/ Speech Scientist Choosing Capgemini means choosing a company where you will be empowered to shape your career in the way you'd like, where you'll be supported and inspired by a collaborative community of colleagues around the world, and where you'll be able to reimagine what's possible. Join us and help the world's leading organizations unlock the value of technology and build a more sustainable, more inclusive world.\nLocation - New York, NY Job Description We are seeking a talented Software Engineer with experience in Natural Language Processing (NLP) to join our team. The focus of this role is to enhance the accuracy and functionality of our systems for interpreting spoken words and phrases, enabling more natural and efficient customer interactions.\nKey Responsibilities:\nImprove the accuracy of system interpretations for spoken words and webchat interactions.\nCollect and curate large datasets of voice samples to train speech recognition models, ensuring recognition across various accents, dialects, and speech patterns.\nImplement advanced NLP techniques to enable complex interactions with callers.\nTest Interactive Voice Response (IVR) systems and webchat interfaces for performance and identify areas for improvement.\nAddress issues such as false positives and misinterpretations in speech recognition.\nStudy customer interactions to understand common errors and adapt models accordingly.\nDevelop and optimize grammar rules, syntax, and semantics for language models.\nWork closely with stakeholders to explain technical concepts in an understandable manner.\nCollaborate with cross-functional teams to ensure project alignment with business goals.\nRequired Skills:\nProficiency in programming languages for speech recognition system development.\nExperience with Linux and Windows environments.\nExperience with Nuance Recognizer, Nuance Dragon Voice, Nuance SpeechSuite, or similar NLU (Natural Language Understanding) platforms.\nAbility to manage and modify NLU performance patterns.\nStrong ability to assess large datasets of speech data to identify patterns and improve model accuracy.\nClear ability to explain complex technical concepts to non-technical stakeholders.\nLife at Capgemini Capgemini supports all aspects of your well-being throughout the changing stages of your life and career. For eligible employees, we offer:\nHealthcare including dental, vision, mental health, and well-being programs\nFinancial well-being programs such as 401(k) and Employee Share Ownership Plan\nPaid time off and paid holidays\nPaid parental leave\nFamily building benefits like adoption assistance, surrogacy, and cryopreservation\nSocial well-being benefits like subsidized back-up child/elder care and tutoring\nMentoring, coaching and learning programs\nEmployee Resource Groups\nDisaster Relief\nDisclaimer:\nCapgemini is an Equal Opportunity Employer encouraging diversity in the workplace. All qualified applicants will receive consideration for employment without regard to race, national origin, gender identity/expression, age, religion, disability, sexual orientation, genetics, veteran status, marital status or any other characteristic protected by law.\nCapgemini is committed to providing reasonable accommodations during our recruitment process. If you need assistance or accommodation, please reach out to your recruiting contact.\nSalary Transparency Capgemini discloses salary range information in compliance with state and local pay transparency obligations. The base salary range for the tagged location is $100,000 - $130,000 /year.\nThis role may be eligible for other compensation including variable compensation, bonus, or commission. Full time regular employees are eligible for paid time off, medical/dental/vision insurance, 401(k), and any other benefits to eligible employees.\nCapgemini is a global business and technology transformation partner, helping organizations to accelerate their dual transition to a digital and sustainable world, while creating tangible impact for enterprises and society.\nRef. code: 150743\nPosted on: Jan 17, 2025\nExperience Level: Experienced Professionals\nContract Type: Permanent\nLocation:\nNew York, US\nBrand: Capgemini\nProfessional Community: Software Engineering\n\n#J-18808-Ljbffr",
            "job_is_remote": false,
            "job_posted_at": "20 hours ago",
            "job_posted_at_timestamp": 1749992400,
            "job_posted_at_datetime_utc": "2025-06-15T13:00:00.000Z",
            "job_location": "New York, NY",
            "job_city": "New York",
            "job_state": "New York",
            "job_country": "US",
            "job_latitude": 40.7127753,
            "job_longitude": -74.0059728,
            "job_benefits": [
                "health_insurance",
                "paid_time_off",
                "dental_coverage"
            ],
            "job_google_link": "https://www.google.com/search?q=jobs&gl=us&hl=en&udm=8#vhid=vt%3D20/docid%3Dq6rqDBIOnPAT4350AAAAAA%3D%3D&vssid=jobs-detail-viewer",
            "job_salary": null,
            "job_min_salary": null,
            "job_max_salary": null,
            "job_salary_period": null,
            "job_highlights": {
                "Qualifications": [
                    "Proficiency in programming languages for speech recognition system development",
                    "Experience with Linux and Windows environments",
                    "Experience with Nuance Recognizer, Nuance Dragon Voice, Nuance SpeechSuite, or similar NLU (Natural Language Understanding) platforms",
                    "Ability to manage and modify NLU performance patterns",
                    "Strong ability to assess large datasets of speech data to identify patterns and improve model accuracy",
                    "Clear ability to explain complex technical concepts to non-technical stakeholders"
                ],
                "Benefits": [
                    "Life at Capgemini Capgemini supports all aspects of your well-being throughout the changing stages of your life and career",
                    "Healthcare including dental, vision, mental health, and well-being programs",
                    "Financial well-being programs such as 401(k) and Employee Share Ownership Plan",
                    "Paid time off and paid holidays",
                    "Paid parental leave",
                    "Family building benefits like adoption assistance, surrogacy, and cryopreservation",
                    "Social well-being benefits like subsidized back-up child/elder care and tutoring",
                    "Mentoring, coaching and learning programs",
                    "The base salary range for the tagged location is $100,000 - $130,000 /year",
                    "This role may be eligible for other compensation including variable compensation, bonus, or commission",
                    "Full time regular employees are eligible for paid time off, medical/dental/vision insurance, 401(k), and any other benefits to eligible employees"
                ],
                "Responsibilities": [
                    "The focus of this role is to enhance the accuracy and functionality of our systems for interpreting spoken words and phrases, enabling more natural and efficient customer interactions",
                    "Improve the accuracy of system interpretations for spoken words and webchat interactions",
                    "Collect and curate large datasets of voice samples to train speech recognition models, ensuring recognition across various accents, dialects, and speech patterns",
                    "Implement advanced NLP techniques to enable complex interactions with callers",
                    "Test Interactive Voice Response (IVR) systems and webchat interfaces for performance and identify areas for improvement",
                    "Address issues such as false positives and misinterpretations in speech recognition",
                    "Study customer interactions to understand common errors and adapt models accordingly",
                    "Develop and optimize grammar rules, syntax, and semantics for language models",
                    "Work closely with stakeholders to explain technical concepts in an understandable manner",
                    "Collaborate with cross-functional teams to ensure project alignment with business goals"
                ]
            },
            "job_onet_soc": "15111100",
            "job_onet_job_zone": "5"
        }
    ]
}